setup.py
data_preprocessing/__init__.py
data_preprocessing/data_preprocessing.py
data_preprocessing.egg-info/PKG-INFO
data_preprocessing.egg-info/SOURCES.txt
data_preprocessing.egg-info/dependency_links.txt
data_preprocessing.egg-info/top_level.txt